ShujuKexueIpythonBijiben/README.md
ShujuKexueIpythonBijiben/__init__.py
ShujuKexueIpythonBijiben/__main__.py
ShujuKexueIpythonBijiben/file.epub
ShujuKexueIpythonBijiben/index.html
ShujuKexueIpythonBijiben/css/__init__.py
ShujuKexueIpythonBijiben/css/annotations.css
ShujuKexueIpythonBijiben/css/main.css
ShujuKexueIpythonBijiben/css/normalize.css
ShujuKexueIpythonBijiben/css/popup.css
ShujuKexueIpythonBijiben/font/__init__.py
ShujuKexueIpythonBijiben/font/fontello.eot
ShujuKexueIpythonBijiben/font/fontello.svg
ShujuKexueIpythonBijiben/font/fontello.ttf
ShujuKexueIpythonBijiben/font/fontello.woff
ShujuKexueIpythonBijiben/img/__init__.py
ShujuKexueIpythonBijiben/img/annotator-glyph-sprite.png
ShujuKexueIpythonBijiben/img/annotator-icon-sprite.png
ShujuKexueIpythonBijiben/img/apple-touch-icon.png
ShujuKexueIpythonBijiben/img/cancelfullscreen.png
ShujuKexueIpythonBijiben/img/close.png
ShujuKexueIpythonBijiben/img/fullscreen.png
ShujuKexueIpythonBijiben/img/loader.gif
ShujuKexueIpythonBijiben/img/menu-icon.png
ShujuKexueIpythonBijiben/img/save.png
ShujuKexueIpythonBijiben/img/saved.png
ShujuKexueIpythonBijiben/img/settings-s.png
ShujuKexueIpythonBijiben/img/settings.png
ShujuKexueIpythonBijiben/img/star.png
ShujuKexueIpythonBijiben/js/__init__.py
ShujuKexueIpythonBijiben/js/epub.js
ShujuKexueIpythonBijiben/js/epub.min.js
ShujuKexueIpythonBijiben/js/epub.min.map
ShujuKexueIpythonBijiben/js/hooks.min.js
ShujuKexueIpythonBijiben/js/hooks.min.map
ShujuKexueIpythonBijiben/js/reader.js
ShujuKexueIpythonBijiben/js/reader.js.map
ShujuKexueIpythonBijiben/js/reader.min.js
ShujuKexueIpythonBijiben/js/reader.min.map
ShujuKexueIpythonBijiben/js/hooks/__init__.py
ShujuKexueIpythonBijiben/js/hooks/extensions/__init__.py
ShujuKexueIpythonBijiben/js/hooks/extensions/highlight.js
ShujuKexueIpythonBijiben/js/libs/__init__.py
ShujuKexueIpythonBijiben/js/libs/jquery.min.js
ShujuKexueIpythonBijiben/js/libs/localforage.min.js
ShujuKexueIpythonBijiben/js/libs/screenfull.js
shuju_kexue_ipython_bijiben-2024.3.5.0.dist-info/METADATA
shuju_kexue_ipython_bijiben-2024.3.5.0.dist-info/WHEEL
shuju_kexue_ipython_bijiben-2024.3.5.0.dist-info/entry_points.txt
shuju_kexue_ipython_bijiben-2024.3.5.0.dist-info/top_level.txt
shuju_kexue_ipython_bijiben-2024.3.5.0.dist-info/RECORD
